{
  "last_link_id": 231,
  "nodes": [
    {
      "mode": 0,
      "outputs": [
        {
          "shape": 3,
          "name": "SAMPLER",
          "links": [
            19
          ],
          "label": "SAMPLER",
          "type": "SAMPLER",
          "localized_name": "SAMPLER"
        }
      ],
      "size": [
        315,
        58
      ],
      "pos": [
        484,
        751
      ],
      "widgets_values": [
        "euler"
      ],
      "inputs": [],
      "flags": {},
      "id": 16,
      "type": "KSamplerSelect",
      "properties": {
        "Node name for S&R": "KSamplerSelect"
      },
      "order": 0
    },
    {
      "mode": 0,
      "outputs": [
        {
          "shape": 3,
          "name": "GUIDER",
          "slot_index": 0,
          "links": [
            30
          ],
          "label": "GUIDER",
          "type": "GUIDER",
          "localized_name": "GUIDER"
        }
      ],
      "size": [
        222.3482666015625,
        46
      ],
      "pos": [
        600,
        0
      ],
      "widgets_values": [],
      "inputs": [
        {
          "name": "model",
          "link": 195,
          "label": "model",
          "type": "MODEL",
          "localized_name": "model"
        },
        {
          "name": "conditioning",
          "link": 129,
          "label": "conditioning",
          "type": "CONDITIONING",
          "localized_name": "conditioning"
        }
      ],
      "flags": {},
      "id": 22,
      "type": "BasicGuider",
      "properties": {
        "Node name for S&R": "BasicGuider"
      },
      "order": 14
    },
    {
      "mode": 0,
      "outputs": [
        {
          "name": "MODEL",
          "slot_index": 0,
          "links": [
            195
          ],
          "label": "MODEL",
          "type": "MODEL",
          "localized_name": "MODEL"
        }
      ],
      "size": [
        210,
        58
      ],
      "pos": [
        360,
        0
      ],
      "widgets_values": [
        7
      ],
      "inputs": [
        {
          "name": "model",
          "link": 223,
          "label": "model",
          "type": "MODEL",
          "localized_name": "model"
        }
      ],
      "flags": {},
      "id": 67,
      "type": "ModelSamplingSD3",
      "properties": {
        "Node name for S&R": "ModelSamplingSD3"
      },
      "order": 11
    },
    {
      "mode": 0,
      "outputs": [
        {
          "shape": 3,
          "name": "output",
          "slot_index": 0,
          "links": [
            181,
            210
          ],
          "label": "output",
          "type": "LATENT",
          "localized_name": "output"
        },
        {
          "shape": 3,
          "name": "denoised_output",
          "label": "denoised_output",
          "type": "LATENT",
          "localized_name": "denoised_output"
        }
      ],
      "size": [
        272.3617858886719,
        326
      ],
      "pos": [
        860,
        200
      ],
      "widgets_values": [],
      "inputs": [
        {
          "name": "noise",
          "link": 37,
          "label": "noise",
          "type": "NOISE",
          "localized_name": "noise"
        },
        {
          "name": "guider",
          "link": 30,
          "label": "guider",
          "type": "GUIDER",
          "localized_name": "guider"
        },
        {
          "name": "sampler",
          "link": 19,
          "label": "sampler",
          "type": "SAMPLER",
          "localized_name": "sampler"
        },
        {
          "name": "sigmas",
          "link": 20,
          "label": "sigmas",
          "type": "SIGMAS",
          "localized_name": "sigmas"
        },
        {
          "name": "latent_image",
          "link": 180,
          "label": "latent_image",
          "type": "LATENT",
          "localized_name": "latent_image"
        }
      ],
      "flags": {},
      "id": 13,
      "type": "SamplerCustomAdvanced",
      "properties": {
        "Node name for S&R": "SamplerCustomAdvanced"
      },
      "order": 15
    },
    {
      "outputs": [
        {
          "shape": 3,
          "name": "NOISE",
          "links": [
            37
          ],
          "label": "NOISE",
          "type": "NOISE",
          "localized_name": "NOISE"
        }
      ],
      "color": "#2a363b",
      "widgets_values": [
        860058970976398,
        "randomize"
      ],
      "inputs": [],
      "flags": {},
      "type": "RandomNoise",
      "mode": 0,
      "bgcolor": "#3f5159",
      "size": [
        315,
        82
      ],
      "pos": [
        479,
        618
      ],
      "id": 25,
      "properties": {
        "Node name for S&R": "RandomNoise"
      },
      "order": 1
    },
    {
      "mode": 0,
      "outputs": [
        {
          "shape": 3,
          "name": "SIGMAS",
          "slot_index": 0,
          "links": [
            20
          ],
          "label": "SIGMAS",
          "type": "SIGMAS",
          "localized_name": "SIGMAS"
        }
      ],
      "size": [
        315,
        106
      ],
      "pos": [
        478,
        860
      ],
      "widgets_values": [
        "simple",
        8,
        1
      ],
      "inputs": [
        {
          "name": "model",
          "link": 224,
          "label": "model",
          "type": "MODEL",
          "localized_name": "model"
        }
      ],
      "flags": {},
      "id": 17,
      "type": "BasicScheduler",
      "properties": {
        "Node name for S&R": "BasicScheduler"
      },
      "order": 12
    },
    {
      "mode": 2,
      "outputs": [
        {
          "name": "IMAGE",
          "slot_index": 0,
          "links": [],
          "label": "IMAGE",
          "type": "IMAGE",
          "localized_name": "IMAGE"
        }
      ],
      "size": [
        210,
        46
      ],
      "pos": [
        1150,
        110
      ],
      "widgets_values": [],
      "inputs": [
        {
          "name": "samples",
          "link": 181,
          "label": "samples",
          "type": "LATENT",
          "localized_name": "samples"
        },
        {
          "name": "vae",
          "link": 206,
          "label": "vae",
          "type": "VAE",
          "localized_name": "vae"
        }
      ],
      "flags": {},
      "id": 8,
      "type": "VAEDecode",
      "properties": {
        "Node name for S&R": "VAEDecode"
      },
      "order": 16
    },
    {
      "outputs": [],
      "color": "#432",
      "widgets_values": [
        "Select a fp8 weight_dtype if you are running out of  memory."
      ],
      "inputs": [],
      "flags": {},
      "type": "Note",
      "mode": 0,
      "bgcolor": "#653",
      "size": [
        350,
        110
      ],
      "pos": [
        -99,
        -74
      ],
      "id": 77,
      "properties": {
        "text": ""
      },
      "order": 3
    },
    {
      "outputs": [
        {
          "shape": 3,
          "name": "CONDITIONING",
          "slot_index": 0,
          "links": [
            129
          ],
          "label": "CONDITIONING",
          "type": "CONDITIONING",
          "localized_name": "CONDITIONING"
        }
      ],
      "color": "#233",
      "widgets_values": [
        10
      ],
      "inputs": [
        {
          "name": "conditioning",
          "link": 175,
          "label": "conditioning",
          "type": "CONDITIONING",
          "localized_name": "conditioning"
        }
      ],
      "flags": {},
      "type": "FluxGuidance",
      "mode": 0,
      "bgcolor": "#355",
      "size": [
        317.4000244140625,
        58
      ],
      "pos": [
        471,
        104
      ],
      "id": 26,
      "properties": {
        "Node name for S&R": "FluxGuidance"
      },
      "order": 13
    },
    {
      "mode": 0,
      "outputs": [
        {
          "name": "IMAGE",
          "slot_index": 0,
          "links": [
            226
          ],
          "label": "IMAGE",
          "type": "IMAGE",
          "localized_name": "IMAGE"
        }
      ],
      "size": [
        210,
        150
      ],
      "pos": [
        1150,
        200
      ],
      "widgets_values": [
        128,
        32,
        64,
        8
      ],
      "inputs": [
        {
          "name": "samples",
          "link": 210,
          "label": "samples",
          "type": "LATENT",
          "localized_name": "samples"
        },
        {
          "name": "vae",
          "link": 211,
          "label": "vae",
          "type": "VAE",
          "localized_name": "vae"
        }
      ],
      "flags": {},
      "id": 73,
      "type": "VAEDecodeTiled",
      "properties": {
        "Node name for S&R": "VAEDecodeTiled"
      },
      "order": 17
    },
    {
      "mode": 0,
      "outputs": [
        {
          "shape": 3,
          "name": "IMAGE",
          "slot_index": 0,
          "links": [
            227
          ],
          "label": "IMAGE",
          "type": "IMAGE",
          "localized_name": "IMAGE"
        }
      ],
      "size": [
        241.79998779296875,
        46
      ],
      "pos": [
        1473,
        160
      ],
      "widgets_values": [],
      "inputs": [
        {
          "name": "upscale_model",
          "link": 228,
          "label": "upscale_model",
          "type": "UPSCALE_MODEL",
          "localized_name": "upscale_model"
        },
        {
          "name": "image",
          "link": 226,
          "label": "image",
          "type": "IMAGE",
          "localized_name": "image"
        }
      ],
      "flags": {},
      "id": 84,
      "type": "ImageUpscaleWithModel",
      "properties": {
        "Node name for S&R": "ImageUpscaleWithModel"
      },
      "order": 18
    },
    {
      "mode": 0,
      "outputs": [
        {
          "shape": 3,
          "name": "UPSCALE_MODEL",
          "links": [
            228
          ],
          "label": "UPSCALE_MODEL",
          "type": "UPSCALE_MODEL",
          "localized_name": "UPSCALE_MODEL"
        }
      ],
      "size": [
        315,
        58
      ],
      "pos": [
        1420,
        45
      ],
      "widgets_values": [
        "RealESRGAN_x2.pth"
      ],
      "inputs": [],
      "flags": {},
      "id": 85,
      "type": "UpscaleModelLoader",
      "properties": {
        "Node name for S&R": "UpscaleModelLoader"
      },
      "order": 4
    },
    {
      "mode": 0,
      "outputs": [
        {
          "shape": 3,
          "name": "Filenames",
          "label": "Filenames",
          "type": "VHS_FILENAMES",
          "localized_name": "Filenames"
        }
      ],
      "size": [
        214.7587890625,
        310
      ],
      "pos": [
        1478,
        239
      ],
      "widgets_values": {
        "save_output": true,
        "filename_prefix": "AnimateDiff",
        "loop_count": 0,
        "pix_fmt": "yuv420p",
        "save_metadata": true,
        "crf": 19,
        "videopreview": {
          "paused": false,
          "hidden": false,
          "params": {
            "filename": "AnimateDiff_00148_cbhmp_1735738075.mp4",
            "format": "video/h264-mp4",
            "subfolder": "",
            "type": "output",
            "frame_rate": 24
          },
          "muted": false
        },
        "format": "video/h264-mp4",
        "frame_rate": 24,
        "pingpong": false
      },
      "inputs": [
        {
          "name": "images",
          "link": 227,
          "label": "images",
          "type": "IMAGE",
          "localized_name": "images"
        },
        {
          "shape": 7,
          "name": "audio",
          "label": "audio",
          "type": "AUDIO",
          "localized_name": "audio"
        },
        {
          "shape": 7,
          "name": "meta_batch",
          "label": "meta_batch",
          "type": "VHS_BatchManager",
          "localized_name": "meta_batch"
        },
        {
          "shape": 7,
          "name": "vae",
          "label": "vae",
          "type": "VAE",
          "localized_name": "vae"
        }
      ],
      "flags": {},
      "id": 83,
      "type": "VHS_VideoCombine",
      "properties": {
        "Node name for S&R": "VHS_VideoCombine"
      },
      "order": 19
    },
    {
      "outputs": [
        {
          "name": "CONDITIONING",
          "slot_index": 0,
          "links": [
            175
          ],
          "label": "CONDITIONING",
          "type": "CONDITIONING",
          "localized_name": "CONDITIONING"
        }
      ],
      "color": "#232",
      "widgets_values": [
        "dabaichui,静态镜头拍摄： 一个韩国美女双手放在在头上，屁股左右扭动",
        [
          false,
          true
        ]
      ],
      "inputs": [
        {
          "name": "clip",
          "link": 205,
          "label": "clip",
          "type": "CLIP",
          "localized_name": "clip"
        }
      ],
      "flags": {},
      "type": "CLIPTextEncode",
      "mode": 0,
      "bgcolor": "#353",
      "size": [
        422.84503173828125,
        164.31304931640625
      ],
      "pos": [
        407.9001159667969,
        216.93995666503906
      ],
      "id": 44,
      "properties": {
        "Node name for S&R": "CLIPTextEncode"
      },
      "order": 10
    },
    {
      "mode": 0,
      "outputs": [
        {
          "shape": 3,
          "name": "CLIP",
          "slot_index": 0,
          "links": [
            205
          ],
          "label": "CLIP",
          "type": "CLIP",
          "localized_name": "CLIP"
        }
      ],
      "size": [
        350,
        130
      ],
      "pos": [
        -83,
        234
      ],
      "widgets_values": [
        "sd3/clip_l.safetensors",
        "llava_llama3_fp8_scaled.safetensors",
        "hunyuan_video",
        "default"
      ],
      "inputs": [],
      "flags": {},
      "id": 11,
      "type": "DualCLIPLoader",
      "properties": {
        "Node name for S&R": "DualCLIPLoader"
      },
      "order": 6
    },
    {
      "mode": 0,
      "outputs": [
        {
          "shape": 3,
          "name": "VAE",
          "slot_index": 0,
          "links": [
            206,
            211
          ],
          "label": "VAE",
          "type": "VAE",
          "localized_name": "VAE"
        }
      ],
      "size": [
        350,
        60
      ],
      "pos": [
        -101,
        416
      ],
      "widgets_values": [
        "hunyuan_video_vae_bf16.safetensors"
      ],
      "inputs": [],
      "flags": {},
      "id": 10,
      "type": "VAELoader",
      "properties": {
        "Node name for S&R": "VAELoader"
      },
      "order": 7
    },
    {
      "mode": 0,
      "outputs": [
        {
          "name": "MODEL",
          "slot_index": 0,
          "links": [
            223,
            224
          ],
          "label": "MODEL",
          "type": "MODEL",
          "localized_name": "MODEL"
        }
      ],
      "size": [
        315,
        82
      ],
      "pos": [
        -60,
        119
      ],
      "widgets_values": [
        "大摆锤200.safetensors",
        1.2
      ],
      "inputs": [
        {
          "name": "model",
          "link": 222,
          "label": "model",
          "type": "MODEL",
          "localized_name": "model"
        }
      ],
      "flags": {},
      "id": 82,
      "type": "LoraLoaderModelOnly",
      "properties": {
        "Node name for S&R": "LoraLoaderModelOnly"
      },
      "order": 9
    },
    {
      "mode": 0,
      "outputs": [
        {
          "name": "LATENT",
          "slot_index": 0,
          "links": [
            180
          ],
          "label": "LATENT",
          "type": "LATENT",
          "localized_name": "LATENT"
        }
      ],
      "size": [
        315,
        130
      ],
      "pos": [
        476,
        433
      ],
      "widgets_values": [
        544,
        960,
        121,
        1
      ],
      "inputs": [],
      "flags": {},
      "id": 45,
      "type": "EmptyHunyuanLatentVideo",
      "properties": {
        "Node name for S&R": "EmptyHunyuanLatentVideo"
      },
      "order": 8
    },
    {
      "outputs": [],
      "color": "#432",
      "widgets_values": [
        "Use the tiled decode node by default because most people will need it.\n\nLower the tile_size and overlap if you run out of memory."
      ],
      "inputs": [],
      "flags": {},
      "type": "Note",
      "mode": 0,
      "bgcolor": "#653",
      "size": [
        210,
        170
      ],
      "pos": [
        1161.6282958984375,
        424.05950927734375
      ],
      "id": 74,
      "properties": {
        "text": ""
      },
      "order": 5
    },
    {
      "mode": 0,
      "outputs": [
        {
          "name": "MODEL",
          "slot_index": 0,
          "links": [
            222
          ],
          "label": "MODEL",
          "type": "MODEL",
          "localized_name": "MODEL"
        }
      ],
      "size": [
        315,
        82
      ],
      "pos": [
        -440,
        150
      ],
      "widgets_values": [
        "hunyuan_video_FastVideo_720_fp8_e4m3fn.safetensors",
        "fp8_e4m3fn"
      ],
      "inputs": [],
      "flags": {},
      "id": 81,
      "type": "UNETLoader",
      "properties": {
        "Node name for S&R": "UNETLoader"
      },
      "order": 2
    }
  ],
  "extra": {
    "workspace_info": {
      "id": "B7mj-kONZOPplfjfMFFI4"
    },
    "ue_links": [],
    "0246.VERSION": [
      0,
      0,
      4
    ],
    "VHS_latentpreviewrate": 0,
    "VHS_latentpreview": false,
    "groupNodes": {},
    "ds": {
      "offset": [
        517.7389530328646,
        131.29623650309563
      ],
      "scale": 1.0610764609500007
    }
  },
  "groups": [],
  "links": [
    [
      19,
      16,
      0,
      13,
      2,
      "SAMPLER"
    ],
    [
      20,
      17,
      0,
      13,
      3,
      "SIGMAS"
    ],
    [
      30,
      22,
      0,
      13,
      1,
      "GUIDER"
    ],
    [
      37,
      25,
      0,
      13,
      0,
      "NOISE"
    ],
    [
      129,
      26,
      0,
      22,
      1,
      "CONDITIONING"
    ],
    [
      175,
      44,
      0,
      26,
      0,
      "CONDITIONING"
    ],
    [
      180,
      45,
      0,
      13,
      4,
      "LATENT"
    ],
    [
      181,
      13,
      0,
      8,
      0,
      "LATENT"
    ],
    [
      195,
      67,
      0,
      22,
      0,
      "MODEL"
    ],
    [
      205,
      11,
      0,
      44,
      0,
      "CLIP"
    ],
    [
      206,
      10,
      0,
      8,
      1,
      "VAE"
    ],
    [
      210,
      13,
      0,
      73,
      0,
      "LATENT"
    ],
    [
      211,
      10,
      0,
      73,
      1,
      "VAE"
    ],
    [
      222,
      81,
      0,
      82,
      0,
      "MODEL"
    ],
    [
      223,
      82,
      0,
      67,
      0,
      "MODEL"
    ],
    [
      224,
      82,
      0,
      17,
      0,
      "MODEL"
    ],
    [
      226,
      73,
      0,
      84,
      1,
      "IMAGE"
    ],
    [
      227,
      84,
      0,
      83,
      0,
      "IMAGE"
    ],
    [
      228,
      85,
      0,
      84,
      0,
      "UPSCALE_MODEL"
    ]
  ],
  "id": "94d1aafa-f31d-4890-bfd9-d7d10764c4e2",
  "config": {},
  "version": 0.4,
  "last_node_id": 89,
  "revision": 0
}